topsis_naveen.py
topsis_naveen-1.3.dist-info/LICENSE.txt
topsis_naveen-1.3.dist-info/METADATA
topsis_naveen-1.3.dist-info/WHEEL
topsis_naveen-1.3.dist-info/entry_points.txt
topsis_naveen-1.3.dist-info/top_level.txt
topsis_naveen-1.3.dist-info/RECORD
