Metadata-Version: 2.1
Name: topsis-naveen
Version: 1.3
Summary: A package used to implement topsis functionality
Home-page: UNKNOWN
Author: Naveen Budhwal
Author-email: nbudhwal_be17@thapar.edu
License: UNKNOWN
Platform: UNKNOWN
Classifier: Programming Language :: Python :: 3
Classifier: License :: OSI Approved :: MIT License
Classifier: Operating System :: OS Independent
Requires-Python: >=3.6
Requires-Dist: numpy
Requires-Dist: pandas
